scrap_imdb-0.1.6.dist-info/METADATA
scrap_imdb-0.1.6.dist-info/RECORD
scrap_imdb-0.1.6.dist-info/WHEEL
scrap_imdb-0.1.6.dist-info/top_level.txt
scrapimdb/__init__.py
scrapimdb/spider.py
