Metadata-Version: 2.1
Name: scrap-imdb
Version: 0.1.6
Summary: Scrap Imdb website to retrieve infdetail informmations from movies or tvshow
Home-page: https://github.com/dsteinberger/scrapimdb
Author: David Steinberger
Author-email: david.steinberger@gmail.com
License: MIT license
Keywords: scrapimdb
Classifier: Development Status :: 2 - Pre-Alpha
Classifier: Intended Audience :: Developers
Classifier: License :: OSI Approved :: MIT License
Classifier: Natural Language :: English
Classifier: Programming Language :: Python :: 3
Classifier: Programming Language :: Python :: 3.4
Classifier: Programming Language :: Python :: 3.5
Classifier: Programming Language :: Python :: 3.6
License-File: LICENSE
License-File: AUTHORS.rst
